emrecharge/__init__.py
emrecharge/app.py
emrecharge/colocation.py
emrecharge/datasets.py
emrecharge/gis.py
emrecharge/metrics.py
emrecharge/rockphysics.py
emrecharge/utils.py
emrecharge/version.py
emrecharge/viz.py
emrecharge-0.0.14.dist-info/LICENSE.md
emrecharge-0.0.14.dist-info/METADATA
emrecharge-0.0.14.dist-info/WHEEL
emrecharge-0.0.14.dist-info/top_level.txt
emrecharge-0.0.14.dist-info/RECORD
